K8sBoot/__init__.py
K8sBoot/boot.py
K8sBoot-1.0.1.dist-info/METADATA
K8sBoot-1.0.1.dist-info/WHEEL
K8sBoot-1.0.1.dist-info/entry_points.txt
K8sBoot-1.0.1.dist-info/top_level.txt
K8sBoot-1.0.1.dist-info/RECORD
